awsad2cli/__init__.py
awsad2cli/__main__.py
awsad2cli/aws_login.py
awsad2cli-0.0.8.dist-info/LICENSE
awsad2cli-0.0.8.dist-info/METADATA
awsad2cli-0.0.8.dist-info/WHEEL
awsad2cli-0.0.8.dist-info/entry_points.txt
awsad2cli-0.0.8.dist-info/top_level.txt
awsad2cli-0.0.8.dist-info/RECORD
